tangled_up_in_unicode/__init__.py
tangled_up_in_unicode/tangled_up_in_unicode_12_0_1.py
tangled_up_in_unicode/tangled_up_in_unicode_13_0_0.py
tangled_up_in_unicode/u13_0_0_data/__init__.py
tangled_up_in_unicode/u13_0_0_data/blocks_to_block_end.py
tangled_up_in_unicode/u13_0_0_data/blocks_to_block_start.py
tangled_up_in_unicode/u13_0_0_data/derived_age_to_age_end.py
tangled_up_in_unicode/u13_0_0_data/derived_age_to_age_start.py
tangled_up_in_unicode/u13_0_0_data/east_asian_width_to_east_asian_width_end.py
tangled_up_in_unicode/u13_0_0_data/east_asian_width_to_east_asian_width_start.py
tangled_up_in_unicode/u13_0_0_data/prop_list_to_property.py
tangled_up_in_unicode/u13_0_0_data/property_value_alias_age_long_to_short.py
tangled_up_in_unicode/u13_0_0_data/property_value_alias_age_short_to_long.py
tangled_up_in_unicode/u13_0_0_data/property_value_alias_bc_long_to_short.py
tangled_up_in_unicode/u13_0_0_data/property_value_alias_bc_short_to_long.py
tangled_up_in_unicode/u13_0_0_data/property_value_alias_blk_long_to_short.py
tangled_up_in_unicode/u13_0_0_data/property_value_alias_blk_short_to_long.py
tangled_up_in_unicode/u13_0_0_data/property_value_alias_ccc_long_to_short.py
tangled_up_in_unicode/u13_0_0_data/property_value_alias_ccc_short_to_long.py
tangled_up_in_unicode/u13_0_0_data/property_value_alias_ea_long_to_short.py
tangled_up_in_unicode/u13_0_0_data/property_value_alias_ea_short_to_long.py
tangled_up_in_unicode/u13_0_0_data/property_value_alias_gc_long_to_short.py
tangled_up_in_unicode/u13_0_0_data/property_value_alias_gc_short_to_long.py
tangled_up_in_unicode/u13_0_0_data/property_value_alias_sc_long_to_short.py
tangled_up_in_unicode/u13_0_0_data/property_value_alias_sc_short_to_long.py
tangled_up_in_unicode/u13_0_0_data/scripts_to_script_end.py
tangled_up_in_unicode/u13_0_0_data/scripts_to_script_start.py
tangled_up_in_unicode/u13_0_0_data/unicode_data_to_bidirectional_end.py
tangled_up_in_unicode/u13_0_0_data/unicode_data_to_bidirectional_start.py
tangled_up_in_unicode-0.1.0.dist-info/LICENSE
tangled_up_in_unicode-0.1.0.dist-info/METADATA
tangled_up_in_unicode-0.1.0.dist-info/WHEEL
tangled_up_in_unicode-0.1.0.dist-info/top_level.txt
tangled_up_in_unicode-0.1.0.dist-info/RECORD
